Osdental/__init__.py
Osdental/BlobStorage/Storage.py
Osdental/BlobStorage/__init__.py
Osdental/Cli/__init__.py
Osdental/Database/Connection.py
Osdental/Database/UnitOfWork.py
Osdental/Database/UowFactory.py
Osdental/Database/__init__.py
Osdental/Decorators/AuditLog.py
Osdental/Decorators/DecryptedData.py
Osdental/Decorators/Grpc.py
Osdental/Decorators/Retry.py
Osdental/Decorators/SqlDataNormalizer.py
Osdental/Decorators/__init__.py
Osdental/Encryptor/Aes.py
Osdental/Encryptor/Argon2.py
Osdental/Encryptor/Bcrypt.py
Osdental/Encryptor/Jwt.py
Osdental/Encryptor/Rsa.py
Osdental/Encryptor/Sha512.py
Osdental/Encryptor/__init__.py
Osdental/Exception/ControlledException.py
Osdental/Exception/__init__.py
Osdental/ExternalHttp/Client.py
Osdental/ExternalHttp/__init__.py
Osdental/Grpc/__init__.py
Osdental/Grpc/Base/GrpcClientBase.py
Osdental/Grpc/Base/__init__.py
Osdental/Grpc/Client/PortalClient.py
Osdental/Grpc/Client/__init__.py
Osdental/Grpc/Generated/Common_pb2.py
Osdental/Grpc/Generated/Common_pb2_grpc.py
Osdental/Grpc/Generated/Portal_pb2.py
Osdental/Grpc/Generated/Portal_pb2_grpc.py
Osdental/Grpc/Generated/__init__.py
Osdental/InternalHttp/Request.py
Osdental/InternalHttp/Response.py
Osdental/InternalHttp/__init__.py
Osdental/Messaging/AzureServiceBus.py
Osdental/Messaging/Kafka.py
Osdental/Messaging/RabbitMQ.py
Osdental/Messaging/__init__.py
Osdental/Models/CDataIntegration.py
Osdental/Models/Catalog.py
Osdental/Models/Legacy.py
Osdental/Models/Response.py
Osdental/Models/Token.py
Osdental/Models/__init__.py
Osdental/RedisCache/Redis.py
Osdental/RedisCache/__init__.py
Osdental/ServicesBus/ServicesBus.py
Osdental/ServicesBus/TaskQueue.py
Osdental/ServicesBus/__init__.py
Osdental/Shared/Logger.py
Osdental/Shared/__init__.py
Osdental/Shared/Config/__init__.py
Osdental/Shared/Enums/Code.py
Osdental/Shared/Enums/Constant.py
Osdental/Shared/Enums/FileType.py
Osdental/Shared/Enums/GrahpqlOperation.py
Osdental/Shared/Enums/Message.py
Osdental/Shared/Enums/Profile.py
osdental_library-3.13.10.dist-info/METADATA
osdental_library-3.13.10.dist-info/WHEEL
osdental_library-3.13.10.dist-info/entry_points.txt
osdental_library-3.13.10.dist-info/top_level.txt
osdental_library-3.13.10.dist-info/RECORD
